CMakeLists.txt
LICENSE.rst
README.rst
pyproject.toml
setup.py
cbi_toolbox/__init__.py
cbi_toolbox.egg-info/PKG-INFO
cbi_toolbox.egg-info/SOURCES.txt
cbi_toolbox.egg-info/dependency_links.txt
cbi_toolbox.egg-info/not-zip-safe
cbi_toolbox.egg-info/requires.txt
cbi_toolbox.egg-info/top_level.txt
cbi_toolbox/bsplines/__init__.py
cbi_toolbox/bsplines/_change_basis.py
cbi_toolbox/bsplines/_interpolation_conversion.py
cbi_toolbox/parallel/__init__.py
cbi_toolbox/parallel/mpi.py
cbi_toolbox/reconstruct/__init__.py
cbi_toolbox/reconstruct/fpsopt.py
cbi_toolbox/reconstruct/preprocess.py
cbi_toolbox/reconstruct/vhf.py
cbi_toolbox/simu/__init__.py
cbi_toolbox/simu/dynamic.py
cbi_toolbox/simu/imaging.py
cbi_toolbox/simu/optics.py
cbi_toolbox/simu/primitives.py
cbi_toolbox/simu/textures.py
cbi_toolbox/splineradon/__init__.py
cbi_toolbox/splineradon/_filter_sinogram.py
cbi_toolbox/splineradon/_spline_kernel.py
cbi_toolbox/splineradon/src/cradon.cpp
cbi_toolbox/splineradon/src/cradon.h
cbi_toolbox/splineradon/src/cudaradon.cpp
cbi_toolbox/splineradon/src/cudaradon.cu
cbi_toolbox/splineradon/src/ompradon.cpp
cbi_toolbox/tests/__init__.py
cbi_toolbox/tests/test_bsplines.py
cbi_toolbox/tests/test_deconv.py
cbi_toolbox/tests/test_mpi.py
cbi_toolbox/tests/test_splradon.py
cbi_toolbox/utils/__init__.py
cbi_toolbox/utils/_arrays.py
cbi_toolbox/utils/ome.py
cbi_toolbox/utils/plotting.py
experiments/PAAQ_2023/src/algorithms
experiments/PAAQ_2023/src/experimental
experiments/PAAQ_2023/src/simulations
pybind11/CMakeLists.txt
pybind11/include/pybind11
pybind11/include/pybind11/attr.h
pybind11/include/pybind11/buffer_info.h
pybind11/include/pybind11/cast.h
pybind11/include/pybind11/chrono.h
pybind11/include/pybind11/common.h
pybind11/include/pybind11/complex.h
pybind11/include/pybind11/detail
pybind11/include/pybind11/eigen.h
pybind11/include/pybind11/embed.h
pybind11/include/pybind11/eval.h
pybind11/include/pybind11/functional.h
pybind11/include/pybind11/gil.h
pybind11/include/pybind11/iostream.h
pybind11/include/pybind11/numpy.h
pybind11/include/pybind11/operators.h
pybind11/include/pybind11/options.h
pybind11/include/pybind11/pybind11.h
pybind11/include/pybind11/pytypes.h
