Metadata-Version: 2.1
Name: cbi-toolbox
Version: 1.3
Summary: A python toolbox for computational bioimaging
Home-page: https://github.com/idiap/cbi_toolbox
Author: François Marelli
Author-email: francois.marelli@idiap.ch
License: BSD-3
Requires-Python: >=3.7, <3.11
Provides-Extra: plots
Provides-Extra: mpi
Provides-Extra: docs
Provides-Extra: ome
License-File: LICENSE.rst
